_tbnf/__init__.py
_tbnf/fable_modules/__init__.py
_tbnf/fable_modules/fable_library/__init__.py
_tbnf/fable_modules/fable_library/array.py
_tbnf/fable_modules/fable_library/async_.py
_tbnf/fable_modules/fable_library/async_builder.py
_tbnf/fable_modules/fable_library/big_int.py
_tbnf/fable_modules/fable_library/bit_converter.py
_tbnf/fable_modules/fable_library/boolean.py
_tbnf/fable_modules/fable_library/char.py
_tbnf/fable_modules/fable_library/choice.py
_tbnf/fable_modules/fable_library/date.py
_tbnf/fable_modules/fable_library/date_offset.py
_tbnf/fable_modules/fable_library/decimal.py
_tbnf/fable_modules/fable_library/double.py
_tbnf/fable_modules/fable_library/fsharp_collections.py
_tbnf/fable_modules/fable_library/fsharp_core.py
_tbnf/fable_modules/fable_library/global_.py
_tbnf/fable_modules/fable_library/guid.py
_tbnf/fable_modules/fable_library/int32.py
_tbnf/fable_modules/fable_library/list.py
_tbnf/fable_modules/fable_library/long.py
_tbnf/fable_modules/fable_library/mailbox_processor.py
_tbnf/fable_modules/fable_library/map.py
_tbnf/fable_modules/fable_library/map_util.py
_tbnf/fable_modules/fable_library/mutable_map.py
_tbnf/fable_modules/fable_library/mutable_set.py
_tbnf/fable_modules/fable_library/native.py
_tbnf/fable_modules/fable_library/numeric.py
_tbnf/fable_modules/fable_library/option.py
_tbnf/fable_modules/fable_library/range.py
_tbnf/fable_modules/fable_library/reflection.py
_tbnf/fable_modules/fable_library/reg_exp.py
_tbnf/fable_modules/fable_library/seq.py
_tbnf/fable_modules/fable_library/seq2.py
_tbnf/fable_modules/fable_library/set.py
_tbnf/fable_modules/fable_library/string.py
_tbnf/fable_modules/fable_library/system_collections_generic.py
_tbnf/fable_modules/fable_library/system_text.py
_tbnf/fable_modules/fable_library/task.py
_tbnf/fable_modules/fable_library/task_builder.py
_tbnf/fable_modules/fable_library/time_span.py
_tbnf/fable_modules/fable_library/timer.py
_tbnf/fable_modules/fable_library/types.py
pykg_manager-0.1.2.dist-info/entry_points.txt
pykg_manager-0.1.2.dist-info/WHEEL
pykg_manager-0.1.2.dist-info/METADATA
pykg_manager-0.1.2.dist-info/RECORD
